<annotation>
	<folder>图片</folder>
	<filename>IMG20231004144604.jpg</filename>
	<path>C:\Users\86131\Desktop\tupisn\图片\IMG20231004144604.jpg</path>
	<source>
		<database>Unknown</database>
	</source>
	<size>
		<width>4096</width>
		<height>3072</height>
		<depth>3</depth>
	</size>
	<segmented>0</segmented>
	<object>
		<name>Text</name>
		<pose>Unspecified</pose>
		<truncated>0</truncated>
		<difficult>0</difficult>
		<bndbox>
			<xmin>82</xmin>
			<ymin>139</ymin>
			<xmax>229</xmax>
			<ymax>855</ymax>
		</bndbox>
	</object>
	<object>
		<name>Text</name>
		<pose>Unspecified</pose>
		<truncated>0</truncated>
		<difficult>0</difficult>
		<bndbox>
			<xmin>446</xmin>
			<ymin>105</ymin>
			<xmax>3312</xmax>
			<ymax>972</ymax>
		</bndbox>
	</object>
	<object>
		<name>Figure</name>
		<pose>Unspecified</pose>
		<truncated>1</truncated>
		<difficult>0</difficult>
		<bndbox>
			<xmin>3292</xmin>
			<ymin>112</ymin>
			<xmax>4096</xmax>
			<ymax>912</ymax>
		</bndbox>
	</object>
	<object>
		<name>Text</name>
		<pose>Unspecified</pose>
		<truncated>1</truncated>
		<difficult>0</difficult>
		<bndbox>
			<xmin>3152</xmin>
			<ymin>972</ymin>
			<xmax>4096</xmax>
			<ymax>1972</ymax>
		</bndbox>
	</object>
	<object>
		<name>Text</name>
		<pose>Unspecified</pose>
		<truncated>1</truncated>
		<difficult>0</difficult>
		<bndbox>
			<xmin>3166</xmin>
			<ymin>1992</ymin>
			<xmax>4096</xmax>
			<ymax>3009</ymax>
		</bndbox>
	</object>
	<object>
		<name>Text</name>
		<pose>Unspecified</pose>
		<truncated>0</truncated>
		<difficult>0</difficult>
		<bndbox>
			<xmin>3086</xmin>
			<ymin>1829</ymin>
			<xmax>3186</xmax>
			<ymax>2065</ymax>
		</bndbox>
	</object>
	<object>
		<name>Text</name>
		<pose>Unspecified</pose>
		<truncated>0</truncated>
		<difficult>0</difficult>
		<bndbox>
			<xmin>29</xmin>
			<ymin>1019</ymin>
			<xmax>2869</xmax>
			<ymax>2022</ymax>
		</bndbox>
	</object>
	<object>
		<name>Text</name>
		<pose>Unspecified</pose>
		<truncated>0</truncated>
		<difficult>0</difficult>
		<bndbox>
			<xmin>1639</xmin>
			<ymin>2069</ymin>
			<xmax>2906</xmax>
			<ymax>3022</ymax>
		</bndbox>
	</object>
	<object>
		<name>Figure</name>
		<pose>Unspecified</pose>
		<truncated>0</truncated>
		<difficult>0</difficult>
		<bndbox>
			<xmin>796</xmin>
			<ymin>2069</ymin>
			<xmax>1636</xmax>
			<ymax>3039</ymax>
		</bndbox>
	</object>
	<object>
		<name>Text</name>
		<pose>Unspecified</pose>
		<truncated>0</truncated>
		<difficult>0</difficult>
		<bndbox>
			<xmin>536</xmin>
			<ymin>2152</ymin>
			<xmax>722</xmax>
			<ymax>3055</ymax>
		</bndbox>
	</object>
	<object>
		<name>Text</name>
		<pose>Unspecified</pose>
		<truncated>0</truncated>
		<difficult>0</difficult>
		<bndbox>
			<xmin>719</xmin>
			<ymin>2805</ymin>
			<xmax>816</xmax>
			<ymax>3002</ymax>
		</bndbox>
	</object>
	<object>
		<name>Text</name>
		<pose>Unspecified</pose>
		<truncated>0</truncated>
		<difficult>0</difficult>
		<bndbox>
			<xmin>99</xmin>
			<ymin>2255</ymin>
			<xmax>266</xmax>
			<ymax>2865</ymax>
		</bndbox>
	</object>
</annotation>
