<annotation>
	<folder>图片</folder>
	<filename>IMG20231004141817.jpg</filename>
	<path>C:\Users\86131\Desktop\tupisn\图片\IMG20231004141817.jpg</path>
	<source>
		<database>Unknown</database>
	</source>
	<size>
		<width>3072</width>
		<height>4096</height>
		<depth>3</depth>
	</size>
	<segmented>0</segmented>
	<object>
		<name>Text</name>
		<pose>Unspecified</pose>
		<truncated>0</truncated>
		<difficult>0</difficult>
		<bndbox>
			<xmin>19</xmin>
			<ymin>157</ymin>
			<xmax>1410</xmax>
			<ymax>3325</ymax>
		</bndbox>
	</object>
	<object>
		<name>Text</name>
		<pose>Unspecified</pose>
		<truncated>0</truncated>
		<difficult>0</difficult>
		<bndbox>
			<xmin>10</xmin>
			<ymin>3352</ymin>
			<xmax>1442</xmax>
			<ymax>3971</ymax>
		</bndbox>
	</object>
	<object>
		<name>Figure</name>
		<pose>Unspecified</pose>
		<truncated>0</truncated>
		<difficult>0</difficult>
		<bndbox>
			<xmin>1442</xmin>
			<ymin>175</ymin>
			<xmax>2783</xmax>
			<ymax>825</ymax>
		</bndbox>
	</object>
	<object>
		<name>Text</name>
		<pose>Unspecified</pose>
		<truncated>0</truncated>
		<difficult>0</difficult>
		<bndbox>
			<xmin>1729</xmin>
			<ymin>793</ymin>
			<xmax>2397</xmax>
			<ymax>893</ymax>
		</bndbox>
	</object>
	<object>
		<name>Text</name>
		<pose>Unspecified</pose>
		<truncated>0</truncated>
		<difficult>0</difficult>
		<bndbox>
			<xmin>1429</xmin>
			<ymin>907</ymin>
			<xmax>2806</xmax>
			<ymax>2134</ymax>
		</bndbox>
	</object>
	<object>
		<name>Figure</name>
		<pose>Unspecified</pose>
		<truncated>0</truncated>
		<difficult>0</difficult>
		<bndbox>
			<xmin>1451</xmin>
			<ymin>2139</ymin>
			<xmax>2815</xmax>
			<ymax>3043</ymax>
		</bndbox>
	</object>
	<object>
		<name>Text</name>
		<pose>Unspecified</pose>
		<truncated>0</truncated>
		<difficult>0</difficult>
		<bndbox>
			<xmin>1756</xmin>
			<ymin>3039</ymin>
			<xmax>2497</xmax>
			<ymax>3134</ymax>
		</bndbox>
	</object>
	<object>
		<name>Text</name>
		<pose>Unspecified</pose>
		<truncated>0</truncated>
		<difficult>0</difficult>
		<bndbox>
			<xmin>1419</xmin>
			<ymin>3143</ymin>
			<xmax>2897</xmax>
			<ymax>3957</ymax>
		</bndbox>
	</object>
</annotation>
