<annotation>
	<folder>img_data</folder>
	<filename>z_img_218.jpg</filename>
	<path>D:\img_data\z_img_218.jpg</path>
	<source>
		<database>Unknown</database>
	</source>
	<size>
		<width>3120</width>
		<height>4208</height>
		<depth>3</depth>
	</size>
	<segmented>0</segmented>
	<object>
		<name>Text</name>
		<pose>Unspecified</pose>
		<truncated>0</truncated>
		<difficult>0</difficult>
		<bndbox>
			<xmin>1100</xmin>
			<ymin>227</ymin>
			<xmax>1659</xmax>
			<ymax>306</ymax>
		</bndbox>
	</object>
	<object>
		<name>Text</name>
		<pose>Unspecified</pose>
		<truncated>0</truncated>
		<difficult>0</difficult>
		<bndbox>
			<xmin>2356</xmin>
			<ymin>218</ymin>
			<xmax>2459</xmax>
			<ymax>285</ymax>
		</bndbox>
	</object>
	<object>
		<name>Text</name>
		<pose>Unspecified</pose>
		<truncated>0</truncated>
		<difficult>0</difficult>
		<bndbox>
			<xmin>242</xmin>
			<ymin>356</ymin>
			<xmax>2526</xmax>
			<ymax>736</ymax>
		</bndbox>
	</object>
	<object>
		<name>Figure</name>
		<pose>Unspecified</pose>
		<truncated>0</truncated>
		<difficult>0</difficult>
		<bndbox>
			<xmin>409</xmin>
			<ymin>770</ymin>
			<xmax>2368</xmax>
			<ymax>1617</ymax>
		</bndbox>
	</object>
	<object>
		<name>Text</name>
		<pose>Unspecified</pose>
		<truncated>0</truncated>
		<difficult>0</difficult>
		<bndbox>
			<xmin>400</xmin>
			<ymin>1629</ymin>
			<xmax>2411</xmax>
			<ymax>1692</ymax>
		</bndbox>
	</object>
	<object>
		<name>Figure</name>
		<pose>Unspecified</pose>
		<truncated>0</truncated>
		<difficult>0</difficult>
		<bndbox>
			<xmin>552</xmin>
			<ymin>2159</ymin>
			<xmax>844</xmax>
			<ymax>3108</ymax>
		</bndbox>
	</object>
	<object>
		<name>Figure</name>
		<pose>Unspecified</pose>
		<truncated>0</truncated>
		<difficult>0</difficult>
		<bndbox>
			<xmin>902</xmin>
			<ymin>1720</ymin>
			<xmax>1194</xmax>
			<ymax>3458</ymax>
		</bndbox>
	</object>
	<object>
		<name>Figure</name>
		<pose>Unspecified</pose>
		<truncated>0</truncated>
		<difficult>0</difficult>
		<bndbox>
			<xmin>1209</xmin>
			<ymin>1706</ymin>
			<xmax>1429</xmax>
			<ymax>3403</ymax>
		</bndbox>
	</object>
	<object>
		<name>Figure</name>
		<pose>Unspecified</pose>
		<truncated>0</truncated>
		<difficult>0</difficult>
		<bndbox>
			<xmin>1464</xmin>
			<ymin>1705</ymin>
			<xmax>1635</xmax>
			<ymax>3430</ymax>
		</bndbox>
	</object>
	<object>
		<name>Figure</name>
		<pose>Unspecified</pose>
		<truncated>0</truncated>
		<difficult>0</difficult>
		<bndbox>
			<xmin>1635</xmin>
			<ymin>1706</ymin>
			<xmax>1853</xmax>
			<ymax>3415</ymax>
		</bndbox>
	</object>
	<object>
		<name>Figure</name>
		<pose>Unspecified</pose>
		<truncated>0</truncated>
		<difficult>0</difficult>
		<bndbox>
			<xmin>1861</xmin>
			<ymin>1762</ymin>
			<xmax>1982</xmax>
			<ymax>3415</ymax>
		</bndbox>
	</object>
	<object>
		<name>Figure</name>
		<pose>Unspecified</pose>
		<truncated>0</truncated>
		<difficult>0</difficult>
		<bndbox>
			<xmin>2076</xmin>
			<ymin>1703</ymin>
			<xmax>2288</xmax>
			<ymax>3427</ymax>
		</bndbox>
	</object>
	<object>
		<name>Text</name>
		<pose>Unspecified</pose>
		<truncated>0</truncated>
		<difficult>0</difficult>
		<bndbox>
			<xmin>321</xmin>
			<ymin>3458</ymin>
			<xmax>2592</xmax>
			<ymax>3630</ymax>
		</bndbox>
	</object>
</annotation>
