<annotation>
	<folder>img_data</folder>
	<filename>z_img_087.jpg</filename>
	<path>D:\img_data\z_img_087.jpg</path>
	<source>
		<database>Unknown</database>
	</source>
	<size>
		<width>3120</width>
		<height>4208</height>
		<depth>3</depth>
	</size>
	<segmented>0</segmented>
	<object>
		<name>Text</name>
		<pose>Unspecified</pose>
		<truncated>0</truncated>
		<difficult>0</difficult>
		<bndbox>
			<xmin>1109</xmin>
			<ymin>109</ymin>
			<xmax>1758</xmax>
			<ymax>198</ymax>
		</bndbox>
	</object>
	<object>
		<name>Text</name>
		<pose>Unspecified</pose>
		<truncated>0</truncated>
		<difficult>0</difficult>
		<bndbox>
			<xmin>2452</xmin>
			<ymin>123</ymin>
			<xmax>2608</xmax>
			<ymax>179</ymax>
		</bndbox>
	</object>
	<object>
		<name>Text</name>
		<pose>Unspecified</pose>
		<truncated>0</truncated>
		<difficult>0</difficult>
		<bndbox>
			<xmin>280</xmin>
			<ymin>239</ymin>
			<xmax>2697</xmax>
			<ymax>500</ymax>
		</bndbox>
	</object>
	<object>
		<name>Text</name>
		<pose>Unspecified</pose>
		<truncated>0</truncated>
		<difficult>0</difficult>
		<bndbox>
			<xmin>356</xmin>
			<ymin>520</ymin>
			<xmax>939</xmax>
			<ymax>641</ymax>
		</bndbox>
	</object>
	<object>
		<name>Text</name>
		<pose>Unspecified</pose>
		<truncated>0</truncated>
		<difficult>0</difficult>
		<bndbox>
			<xmin>253</xmin>
			<ymin>648</ymin>
			<xmax>2674</xmax>
			<ymax>827</ymax>
		</bndbox>
	</object>
	<object>
		<name>Text</name>
		<pose>Unspecified</pose>
		<truncated>0</truncated>
		<difficult>0</difficult>
		<bndbox>
			<xmin>255</xmin>
			<ymin>824</ymin>
			<xmax>2670</xmax>
			<ymax>1183</ymax>
		</bndbox>
	</object>
	<object>
		<name>Text</name>
		<pose>Unspecified</pose>
		<truncated>0</truncated>
		<difficult>0</difficult>
		<bndbox>
			<xmin>238</xmin>
			<ymin>1282</ymin>
			<xmax>976</xmax>
			<ymax>1376</ymax>
		</bndbox>
	</object>
	<object>
		<name>Text</name>
		<pose>Unspecified</pose>
		<truncated>0</truncated>
		<difficult>0</difficult>
		<bndbox>
			<xmin>2518</xmin>
			<ymin>1186</ymin>
			<xmax>2680</xmax>
			<ymax>1259</ymax>
		</bndbox>
	</object>
	<object>
		<name>Text</name>
		<pose>Unspecified</pose>
		<truncated>0</truncated>
		<difficult>0</difficult>
		<bndbox>
			<xmin>211</xmin>
			<ymin>1545</ymin>
			<xmax>2686</xmax>
			<ymax>1723</ymax>
		</bndbox>
	</object>
	<object>
		<name>Equation</name>
		<pose>Unspecified</pose>
		<truncated>0</truncated>
		<difficult>0</difficult>
		<bndbox>
			<xmin>1067</xmin>
			<ymin>1209</ymin>
			<xmax>1741</xmax>
			<ymax>1315</ymax>
		</bndbox>
	</object>
	<object>
		<name>Equation</name>
		<pose>Unspecified</pose>
		<truncated>0</truncated>
		<difficult>0</difficult>
		<bndbox>
			<xmin>1071</xmin>
			<ymin>1370</ymin>
			<xmax>1756</xmax>
			<ymax>1556</ymax>
		</bndbox>
	</object>
	<object>
		<name>Equation</name>
		<pose>Unspecified</pose>
		<truncated>0</truncated>
		<difficult>0</difficult>
		<bndbox>
			<xmin>912</xmin>
			<ymin>1735</ymin>
			<xmax>1905</xmax>
			<ymax>1944</ymax>
		</bndbox>
	</object>
	<object>
		<name>Text</name>
		<pose>Unspecified</pose>
		<truncated>0</truncated>
		<difficult>0</difficult>
		<bndbox>
			<xmin>2506</xmin>
			<ymin>1802</ymin>
			<xmax>2690</xmax>
			<ymax>1870</ymax>
		</bndbox>
	</object>
	<object>
		<name>Text</name>
		<pose>Unspecified</pose>
		<truncated>0</truncated>
		<difficult>0</difficult>
		<bndbox>
			<xmin>2527</xmin>
			<ymin>2250</ymin>
			<xmax>2676</xmax>
			<ymax>2335</ymax>
		</bndbox>
	</object>
	<object>
		<name>Text</name>
		<pose>Unspecified</pose>
		<truncated>0</truncated>
		<difficult>0</difficult>
		<bndbox>
			<xmin>230</xmin>
			<ymin>1956</ymin>
			<xmax>2670</xmax>
			<ymax>2121</ymax>
		</bndbox>
	</object>
	<object>
		<name>Text</name>
		<pose>Unspecified</pose>
		<truncated>0</truncated>
		<difficult>0</difficult>
		<bndbox>
			<xmin>230</xmin>
			<ymin>2486</ymin>
			<xmax>1633</xmax>
			<ymax>2571</ymax>
		</bndbox>
	</object>
	<object>
		<name>Text</name>
		<pose>Unspecified</pose>
		<truncated>0</truncated>
		<difficult>0</difficult>
		<bndbox>
			<xmin>226</xmin>
			<ymin>2565</ymin>
			<xmax>2730</xmax>
			<ymax>3118</ymax>
		</bndbox>
	</object>
	<object>
		<name>Equation</name>
		<pose>Unspecified</pose>
		<truncated>0</truncated>
		<difficult>0</difficult>
		<bndbox>
			<xmin>955</xmin>
			<ymin>2145</ymin>
			<xmax>1853</xmax>
			<ymax>2474</ymax>
		</bndbox>
	</object>
	<object>
		<name>Text</name>
		<pose>Unspecified</pose>
		<truncated>0</truncated>
		<difficult>0</difficult>
		<bndbox>
			<xmin>711</xmin>
			<ymin>3138</ymin>
			<xmax>2144</xmax>
			<ymax>3230</ymax>
		</bndbox>
	</object>
	<object>
		<name>Table</name>
		<pose>Unspecified</pose>
		<truncated>0</truncated>
		<difficult>0</difficult>
		<bndbox>
			<xmin>530</xmin>
			<ymin>3252</ymin>
			<xmax>2376</xmax>
			<ymax>3762</ymax>
		</bndbox>
	</object>
</annotation>
